pycaf/__init__.py
pycaf/main.py
pycaf-0.2.0.dist-info/METADATA
pycaf-0.2.0.dist-info/WHEEL
pycaf-0.2.0.dist-info/entry_points.txt
pycaf-0.2.0.dist-info/top_level.txt
pycaf-0.2.0.dist-info/RECORD
