Metadata-Version: 2.4
Name: pycaf
Version: 0.2.0
Summary: Python Code Assistant Free. Новая версия 0.2.0
Author-email: Georgii Nikishov <timofeynikishov@yandex.ru>
License: MIT
Requires-Dist: g4f
